grapes/Column.py
grapes/GrapesDatabase.py
grapes/InMemoryGrapesDatabase.py
grapes/Table.py
grapes/__init__.py
grapes/__meta__.py
grapes/Errors/ColumnError.py
grapes/Errors/GetError.py
grapes/Errors/InsertError.py
grapes/Errors/TableError.py
grapes/Errors/__init__.py
grapesdb-1.3.0.dist-info/METADATA
grapesdb-1.3.0.dist-info/WHEEL
grapesdb-1.3.0.dist-info/top_level.txt
grapesdb-1.3.0.dist-info/RECORD
