Metadata-Version: 2.1
Name: grapesdb
Version: 1.3.0
Summary: THE way to store data.
Home-page: https://github.com/ItsTato/grapes
Author: ItsTato
Author-email: thatpogcomputer@gmail.com
Classifier: Programming Language :: Python :: 3
Classifier: Development Status :: 4 - Beta
Classifier: Intended Audience :: Developers
Classifier: License :: OSI Approved :: BSD License
Classifier: Operating System :: OS Independent
Requires-Python: >=3.10
